dewakss/__init__.py
dewakss/decomposition.py
dewakss/denoise.py
dewakss/utils.py
DEWAKSS-1.0.1.dist-info/METADATA
DEWAKSS-1.0.1.dist-info/WHEEL
DEWAKSS-1.0.1.dist-info/top_level.txt
DEWAKSS-1.0.1.dist-info/RECORD
