Metadata-Version: 2.1
Name: DEWAKSS
Version: 1.0.1
Summary: Denoising Expression data with a Weighted Affinity Kernel and Self-Supervision.
Home-page: https://gitlab.com/Xparx/dewakss
Author: Andreas Tjarnberg
Author-email: andreas.tjarnberg@nyu.edu
License: LGPL
Requires-Python: >=3.6
Requires-Dist: sparse-dot-mkl
Requires-Dist: umap-learn (>=0.5.0)
Requires-Dist: pynndescent
Requires-Dist: scipy
Requires-Dist: scikit-learn
Requires-Dist: leidenalg
Requires-Dist: pandas
Requires-Dist: scanpy (>=1.5.1)
Requires-Dist: matplotlib
Requires-Dist: seaborn
